querio/__init__.py
querio/interface.py
querio/queryobject.py
querio/db/__init__.py
querio/db/data_accessor.py
querio/db/exceptions/__init__.py
querio/db/exceptions/querio_database_error.py
querio/ml/__init__.py
querio/ml/model.py
querio/ml/noderesult.py
querio/ml/prediction.py
querio/ml/treetraversal.py
querio/ml/utils.py
querio/ml/expression/__init__.py
querio/ml/expression/cond.py
querio/ml/expression/expression.py
querio/ml/expression/expressionnode.py
querio/ml/expression/feature.py
querio/service/__init__.py
querio/service/save_service.py
querio/service/utils.py
querio/service/exceptions/__init__.py
querio/service/exceptions/querio_file_error.py
tests/__init__.py
tests/test_interface.py
tests/test_travis_normalized_db.py
tests/testscript.py
tests/ml/__init__.py
tests/ml/test_expressionnode.py
tests/ml/test_feature.py
tests/ml/test_model.py
tests/ml/test_prediction.py
tests/ml/test_treetraversal.py
tests/ml/test_utils.py
tests/service/__init__.py
tests/service/test_save_service.py
tests/service/test_utils.py
querio-0.0.2.dist-info/LICENSE
querio-0.0.2.dist-info/METADATA
querio-0.0.2.dist-info/WHEEL
querio-0.0.2.dist-info/top_level.txt
querio-0.0.2.dist-info/RECORD
