Metadata-Version: 2.1
Name: querio
Version: 0.0.2
Summary: A python library for quickly estimating database results
Home-page: UNKNOWN
Author: 
Author-email: 
License: UNKNOWN
Platform: UNKNOWN
Classifier: Programming Language :: Python :: 3
Classifier: License :: OSI Approved :: MIT License
Classifier: Operating System :: OS Independent
